[
  {"table": {
    "name": "sex_types",
    "description": "Sexes.",
    "type": "types",
    "values": [
      {
        "name": "neutral",
        "bit": 0,
        "settable": true
      },
      {
        "name": "male",
        "bit": 1,
        "settable": true
      },
      {
        "name": "female",
        "bit": 2,
        "settable": true
      },
      {
        "name": "random",
        "bit": 3,
        "settable": true
      }
    ]
  }},
  {"table": {
    "name": "affect_apply_types",
    "description": "Affect apply types.",
    "type": "types",
    "values": [
      {
        "name": "none",
        "bit": 0,
        "settable": true
      },
      {
        "name": "strength",
        "bit": 1,
        "settable": true
      },
      {
        "name": "dexterity",
        "bit": 2,
        "settable": true
      },
      {
        "name": "intelligence",
        "bit": 3,
        "settable": true
      },
      {
        "name": "wisdom",
        "bit": 4,
        "settable": true
      },
      {
        "name": "constitution",
        "bit": 5,
        "settable": true
      },
      {
        "name": "sex",
        "bit": 6,
        "settable": true
      },
      {
        "name": "class",
        "bit": 7,
        "settable": true
      },
      {
        "name": "level",
        "bit": 8,
        "settable": true
      },
      {
        "name": "age",
        "bit": 9,
        "settable": true
      },
      {
        "name": "height",
        "bit": 10,
        "settable": true
      },
      {
        "name": "weight",
        "bit": 11,
        "settable": true
      },
      {
        "name": "mana",
        "bit": 12,
        "settable": true
      },
      {
        "name": "hp",
        "bit": 13,
        "settable": true
      },
      {
        "name": "moves",
        "bit": 14,
        "settable": true
      },
      {
        "name": "gold",
        "bit": 15,
        "settable": true
      },
      {
        "name": "experience",
        "bit": 16,
        "settable": true
      },
      {
        "name": "armor class",
        "bit": 17,
        "settable": true
      },
      {
        "name": "hit roll",
        "bit": 18,
        "settable": true
      },
      {
        "name": "damage roll",
        "bit": 19,
        "settable": true
      },
      {
        "name": "saves",
        "bit": 20,
        "settable": true
      },
      {
        "name": "save vs rod",
        "bit": 21,
        "settable": true
      },
      {
        "name": "save vs petrification",
        "bit": 22,
        "settable": true
      },
      {
        "name": "save vs breath",
        "bit": 23,
        "settable": true
      },
      {
        "name": "save vs spell",
        "bit": 24,
        "settable": true
      },
      {
        "name": "spell affect",
        "bit": 25,
        "settable": false
      }
    ]
  }},
  {"table": {
    "name": "wear_loc_phrases",
    "description": "Phrases for wear locations.",
    "type": "types",
    "values": [
      {
        "name": "as a light",
        "bit": 0,
        "settable": true
      },
      {
        "name": "on the left finger",
        "bit": 1,
        "settable": true
      },
      {
        "name": "on the right finger",
        "bit": 2,
        "settable": true
      },
      {
        "name": "around the neck (1)",
        "bit": 3,
        "settable": true
      },
      {
        "name": "around the neck (2)",
        "bit": 4,
        "settable": true
      },
      {
        "name": "on the body",
        "bit": 5,
        "settable": true
      },
      {
        "name": "over the head",
        "bit": 6,
        "settable": true
      },
      {
        "name": "on the legs",
        "bit": 7,
        "settable": true
      },
      {
        "name": "on the feet",
        "bit": 8,
        "settable": true
      },
      {
        "name": "on the hands",
        "bit": 9,
        "settable": true
      },
      {
        "name": "on the arms",
        "bit": 10,
        "settable": true
      },
      {
        "name": "as a shield",
        "bit": 11,
        "settable": true
      },
      {
        "name": "about the shoulders",
        "bit": 12,
        "settable": true
      },
      {
        "name": "around the waist",
        "bit": 13,
        "settable": true
      },
      {
        "name": "on the left wrist",
        "bit": 14,
        "settable": true
      },
      {
        "name": "on the right wrist",
        "bit": 15,
        "settable": true
      },
      {
        "name": "wielded",
        "bit": 16,
        "settable": true
      },
      {
        "name": "held in the hands",
        "bit": 17,
        "settable": true
      },
      {
        "name": "floating nearby",
        "bit": 18,
        "settable": true
      },
      {
        "name": "in the inventory",
        "bit": -1,
        "settable": true
      }
    ]
  }},
  {"table": {
    "name": "wear_loc_types",
    "description": "Where mobile wears object.",
    "type": "types",
    "values": [
      {
        "name": "light",
        "bit": 0,
        "settable": true
      },
      {
        "name": "lfinger",
        "bit": 1,
        "settable": true
      },
      {
        "name": "rfinger",
        "bit": 2,
        "settable": true
      },
      {
        "name": "neck1",
        "bit": 3,
        "settable": true
      },
      {
        "name": "neck2",
        "bit": 4,
        "settable": true
      },
      {
        "name": "body",
        "bit": 5,
        "settable": true
      },
      {
        "name": "head",
        "bit": 6,
        "settable": true
      },
      {
        "name": "legs",
        "bit": 7,
        "settable": true
      },
      {
        "name": "feet",
        "bit": 8,
        "settable": true
      },
      {
        "name": "hands",
        "bit": 9,
        "settable": true
      },
      {
        "name": "arms",
        "bit": 10,
        "settable": true
      },
      {
        "name": "shield",
        "bit": 11,
        "settable": true
      },
      {
        "name": "about",
        "bit": 12,
        "settable": true
      },
      {
        "name": "waist",
        "bit": 13,
        "settable": true
      },
      {
        "name": "lwrist",
        "bit": 14,
        "settable": true
      },
      {
        "name": "rwrist",
        "bit": 15,
        "settable": true
      },
      {
        "name": "wielded",
        "bit": 16,
        "settable": true
      },
      {
        "name": "hold",
        "bit": 17,
        "settable": true
      },
      {
        "name": "floating",
        "bit": 18,
        "settable": true
      },
      {
        "name": "none",
        "bit": -1,
        "settable": true
      }
    ]
  }},
  {"table": {
    "name": "ac_types",
    "description": "AC for different attacks.",
    "type": "types",
    "values": [
      {
        "name": "pierce",
        "bit": 0,
        "settable": true
      },
      {
        "name": "bash",
        "bit": 1,
        "settable": true
      },
      {
        "name": "slash",
        "bit": 2,
        "settable": true
      },
      {
        "name": "magic",
        "bit": 3,
        "settable": true
      }
    ]
  }},
  {"table": {
    "name": "size_types",
    "description": "Mobile sizes.",
    "type": "types",
    "values": [
      {
        "name": "tiny",
        "bit": 0,
        "settable": true
      },
      {
        "name": "small",
        "bit": 1,
        "settable": true
      },
      {
        "name": "medium",
        "bit": 2,
        "settable": true
      },
      {
        "name": "large",
        "bit": 3,
        "settable": true
      },
      {
        "name": "huge",
        "bit": 4,
        "settable": true
      },
      {
        "name": "giant",
        "bit": 5,
        "settable": true
      }
    ]
  }},
  {"table": {
    "name": "weapon_types",
    "description": "Weapon classes.",
    "type": "types",
    "values": [
      {
        "name": "exotic",
        "bit": 0,
        "settable": true
      },
      {
        "name": "sword",
        "bit": 1,
        "settable": true
      },
      {
        "name": "dagger",
        "bit": 2,
        "settable": true
      },
      {
        "name": "spear",
        "bit": 3,
        "settable": true
      },
      {
        "name": "mace",
        "bit": 4,
        "settable": true
      },
      {
        "name": "axe",
        "bit": 5,
        "settable": true
      },
      {
        "name": "flail",
        "bit": 6,
        "settable": true
      },
      {
        "name": "whip",
        "bit": 7,
        "settable": true
      },
      {
        "name": "polearm",
        "bit": 8,
        "settable": true
      }
    ]
  }},
  {"table": {
    "name": "position_types",
    "description": "Mobile positions.",
    "type": "types",
    "values": [
      {
        "name": "dead",
        "bit": 0,
        "settable": false
      },
      {
        "name": "mortal",
        "bit": 1,
        "settable": false
      },
      {
        "name": "incap",
        "bit": 2,
        "settable": false
      },
      {
        "name": "stunned",
        "bit": 3,
        "settable": false
      },
      {
        "name": "sleeping",
        "bit": 4,
        "settable": true
      },
      {
        "name": "resting",
        "bit": 5,
        "settable": true
      },
      {
        "name": "sitting",
        "bit": 6,
        "settable": true
      },
      {
        "name": "fighting",
        "bit": 7,
        "settable": false
      },
      {
        "name": "standing",
        "bit": 8,
        "settable": true
      }
    ]
  }},
  {"table": {
    "name": "sector_types",
    "description": "Sector types, terrain.",
    "type": "types",
    "values": [
      {
        "name": "inside",
        "bit": 0,
        "settable": true
      },
      {
        "name": "city",
        "bit": 1,
        "settable": true
      },
      {
        "name": "field",
        "bit": 2,
        "settable": true
      },
      {
        "name": "forest",
        "bit": 3,
        "settable": true
      },
      {
        "name": "hills",
        "bit": 4,
        "settable": true
      },
      {
        "name": "mountain",
        "bit": 5,
        "settable": true
      },
      {
        "name": "swim",
        "bit": 6,
        "settable": true
      },
      {
        "name": "noswim",
        "bit": 7,
        "settable": true
      },
      {
        "name": "unused",
        "bit": 8,
        "settable": false
      },
      {
        "name": "air",
        "bit": 9,
        "settable": true
      },
      {
        "name": "desert",
        "bit": 10,
        "settable": true
      }
    ]
  }},
  {"table": {
    "name": "item_types",
    "description": "Types of objects.",
    "type": "types",
    "values": [
      {
        "name": "none",
        "bit": 0,
        "settable": false
      },
      {
        "name": "light",
        "bit": 1,
        "settable": true
      },
      {
        "name": "scroll",
        "bit": 2,
        "settable": true
      },
      {
        "name": "wand",
        "bit": 3,
        "settable": true
      },
      {
        "name": "staff",
        "bit": 4,
        "settable": true
      },
      {
        "name": "weapon",
        "bit": 5,
        "settable": true
      },
      {
        "name": "unused_item_1",
        "bit": 6,
        "settable": false
      },
      {
        "name": "unused_item_2",
        "bit": 7,
        "settable": false
      },
      {
        "name": "treasure",
        "bit": 8,
        "settable": true
      },
      {
        "name": "armor",
        "bit": 9,
        "settable": true
      },
      {
        "name": "potion",
        "bit": 10,
        "settable": true
      },
      {
        "name": "clothing",
        "bit": 11,
        "settable": true
      },
      {
        "name": "furniture",
        "bit": 12,
        "settable": true
      },
      {
        "name": "trash",
        "bit": 13,
        "settable": true
      },
      {
        "name": "unused_item_3",
        "bit": 14,
        "settable": false
      },
      {
        "name": "container",
        "bit": 15,
        "settable": true
      },
      {
        "name": "unused_item_4",
        "bit": 16,
        "settable": false
      },
      {
        "name": "drink",
        "bit": 17,
        "settable": true
      },
      {
        "name": "key",
        "bit": 18,
        "settable": true
      },
      {
        "name": "food",
        "bit": 19,
        "settable": true
      },
      {
        "name": "money",
        "bit": 20,
        "settable": true
      },
      {
        "name": "unused_item_5",
        "bit": 21,
        "settable": false
      },
      {
        "name": "boat",
        "bit": 22,
        "settable": true
      },
      {
        "name": "npc_corpse",
        "bit": 23,
        "settable": true
      },
      {
        "name": "pc_corpse",
        "bit": 24,
        "settable": true
      },
      {
        "name": "fountain",
        "bit": 25,
        "settable": true
      },
      {
        "name": "pill",
        "bit": 26,
        "settable": true
      },
      {
        "name": "protect",
        "bit": 27,
        "settable": true
      },
      {
        "name": "map",
        "bit": 28,
        "settable": true
      },
      {
        "name": "portal",
        "bit": 29,
        "settable": true
      },
      {
        "name": "warp_stone",
        "bit": 30,
        "settable": true
      },
      {
        "name": "room_key",
        "bit": 31,
        "settable": true
      },
      {
        "name": "gem",
        "bit": 32,
        "settable": true
      },
      {
        "name": "jewelry",
        "bit": 33,
        "settable": true
      },
      {
        "name": "jukebox",
        "bit": 34,
        "settable": true
      }
    ]
  }},
  {"table": {
    "name": "door_resets",
    "description": "Door reset types",
    "type": "types",
    "values": [
      {
        "name": "open and unlocked",
        "bit": 0,
        "settable": true
      },
      {
        "name": "closed and unlocked",
        "bit": 1,
        "settable": true
      },
      {
        "name": "closed and locked",
        "bit": 2,
        "settable": true
      }
    ]
  }}
]
